swarmake/__init__.py
swarmake/cmd.py
swarmake/config.py
swarmake/logger.py
swarmake/main.py
swarmake/swarmake.toml
swarmake-0.1.4.dist-info/METADATA
swarmake-0.1.4.dist-info/WHEEL
swarmake-0.1.4.dist-info/entry_points.txt
swarmake-0.1.4.dist-info/licenses/AUTHORS
swarmake-0.1.4.dist-info/licenses/LICENSE
swarmake-0.1.4.dist-info/RECORD
