Metadata-Version: 2.3
Name: swarmake
Version: 0.1.4
Summary: The OpenSwarm Implementation.
Project-URL: Homepage, https://github.com/openswarm-eu/swarmake
Project-URL: Bug Tracker, https://github.com/openswarm-eu/swarmake/issues
Author-email: Geovane Fedrecheski <geovane.fedrecheski@inria.fr>
License: BSD
Classifier: License :: OSI Approved :: BSD License
Classifier: Operating System :: MacOS
Classifier: Operating System :: Microsoft :: Windows
Classifier: Operating System :: POSIX :: Linux
Classifier: Programming Language :: Python :: 3
Requires-Python: >=3.7
Requires-Dist: click==8.1.7
Requires-Dist: rich==13.8.1
Requires-Dist: structlog==24.4.0
Requires-Dist: toml==0.10.2
Requires-Dist: tqdm==4.66.5
